[{"6059081":"Запрос ценовых предложений"},{"6059077":"Запрос ценовых предложений"},{"6059071":"Запрос ценовых предложений"},{"6059062":"Запрос ценовых предложений"},{"6059057":"Запрос ценовых предложений"},{"6059048":"Запрос ценовых предложений"},{"6059045":"Запрос ценовых предложений"},{"6059044":"Запрос ценовых предложений"},{"6059040":"Запрос ценовых предложений"},{"6059039":"Запрос ценовых предложений"},{"6059038":"Запрос ценовых предложений"},{"6059030":"Запрос ценовых предложений"},{"6059025":"Запрос ценовых предложений"},{"6059024":"Запрос ценовых предложений"},{"6059023":"Запрос ценовых предложений"},{"6059017":"Запрос ценовых предложений"},{"6059000":"Запрос ценовых предложений"},{"6058996":"Запрос ценовых предложений"},{"6058989":"Запрос ценовых предложений"},{"6058987":"Запрос ценовых предложений"},{"6058980":"Запрос ценовых предложений"},{"6058976":"Запрос ценовых предложений"},{"6058975":"Запрос ценовых предложений"},{"6058974":"Запрос ценовых предложений"},{"6058973":"Запрос ценовых предложений"},{"6058966":"Запрос ценовых предложений"},{"6058965":"Запрос ценовых предложений"},{"6058963":"Запрос ценовых предложений"},{"6058961":"Запрос ценовых предложений"},{"6058958":"Запрос ценовых предложений"},{"6058957":"Запрос ценовых предложений"},{"6058947":"Запрос ценовых предложений"},{"6058943":"Запрос ценовых предложений"},{"6058940":"Запрос ценовых предложений"},{"6058931":"Запрос ценовых предложений"},{"6058916":"Запрос ценовых предложений"},{"6058915":"Запрос ценовых предложений"},{"6058911":"Запрос ценовых предложений"},{"6058910":"Запрос ценовых предложений"},{"6058908":"Запрос ценовых предложений"},{"6058907":"Запрос ценовых предложений"},{"6058904":"Запрос ценовых предложений"},{"6058903":"Запрос ценовых предложений"},{"6058897":"Запрос ценовых предложений"},{"6058891":"Открытый конкурс"},{"6058890":"Запрос ценовых предложений"},{"6058889":"Запрос ценовых предложений"},{"6058888":"Запрос ценовых предложений"},{"6058887":"Запрос ценовых предложений"},{"6058883":"Запрос ценовых предложений"}]